vidhash/__init__.py
vidhash/frame_hash.py
vidhash/func.py
vidhash/hash_options.py
vidhash/match_options.py
vidhash/py.typed
vidhash/stubs/ffmpy3.pyi
vidhash/stubs/imagehash.pyi
vidhash/video_hash.py
vidhash-0.3.2.dist-info/METADATA
vidhash-0.3.2.dist-info/WHEEL
vidhash-0.3.2.dist-info/licenses/LICENSE
vidhash-0.3.2.dist-info/RECORD
