Metadata-Version: 2.4
Name: vidhash
Version: 0.3.2
Summary: A package for hashing videos and checking for similarity
License: MIT
License-File: LICENSE
Author: Roselyn Coales
Author-email: roselyn@coales.co.uk
Requires-Python: >=3.10,<4.0
Classifier: License :: OSI Approved :: MIT License
Classifier: Programming Language :: Python :: 3
Classifier: Programming Language :: Python :: 3.10
Classifier: Programming Language :: Python :: 3.11
Classifier: Programming Language :: Python :: 3.12
Classifier: Programming Language :: Python :: 3.13
Classifier: Programming Language :: Python :: 3.14
Requires-Dist: ImageHash (>=4.2.1,<5.0.0)
Requires-Dist: Pillow (>=12.1.0,<13.0.0)
Requires-Dist: ffmpy3 (>=0.2.4,<0.3.0)
Requires-Dist: numpy (>=1.22.4,<2.0.0)
Project-URL: Repository, https://github.com/SpangleLabs/vidhash
